LICENSE
MANIFEST.in
README.rst
setup.py
orbitutils/__init__.py
orbitutils/kepler.py
orbitutils/populations.py
orbitutils/utils.py
orbitutils.egg-info/PKG-INFO
orbitutils.egg-info/SOURCES.txt
orbitutils.egg-info/dependency_links.txt
orbitutils.egg-info/not-zip-safe
orbitutils.egg-info/requires.txt
orbitutils.egg-info/top_level.txt
orbitutils/data/Etable.npy
orbitutils/data/Etable_Ms.npy
orbitutils/data/Etable_eccs.npy