Metadata-Version: 1.1
Name: orbitutils
Version: 0.1.5
Summary: Easily make Monte Carlo simulations of binary or triple orbits.
Home-page: https://github.com/timothydmorton/orbitutils
Author: Timothy D. Morton
Author-email: tim.morton@gmail.com
License: UNKNOWN
Platform: UNKNOWN
Classifier: Development Status :: 3 - Alpha
Classifier: Intended Audience :: Science/Research
Classifier: Operating System :: OS Independent
Classifier: Programming Language :: Python
Classifier: Topic :: Scientific/Engineering
Classifier: Topic :: Scientific/Engineering :: Astronomy
